README.rst
setup.py
datastream/__init__.py
datastream/api.py
datastream/exceptions.py
datastream/utils.py
datastream.egg-info/PKG-INFO
datastream.egg-info/SOURCES.txt
datastream.egg-info/dependency_links.txt
datastream.egg-info/not-zip-safe
datastream.egg-info/requires.txt
datastream.egg-info/top_level.txt
datastream/backends/__init__.py
datastream/backends/influxdb.py
datastream/backends/mongodb.py