Metadata-Version: 1.1
Name: datastream
Version: 0.5.0
Summary: Datastream API time-series library.
Home-page: https://github.com/wlanslovenija/datastream
Author: wlan slovenija
Author-email: open@wlan-si.net
License: AGPLv3
Platform: UNKNOWN
Classifier: Development Status :: 4 - Beta
Classifier: Intended Audience :: Developers
Classifier: License :: OSI Approved :: GNU Affero General Public License v3
Classifier: Operating System :: OS Independent
Classifier: Programming Language :: Python
